autotorch/__init__.py
autotorch/version.py
autotorch/core/__init__.py
autotorch/core/decorator.py
autotorch/core/optimizer.py
autotorch/core/space.py
autotorch/core/task.py
autotorch/scheduler/__init__.py
autotorch/scheduler/fifo.py
autotorch/scheduler/hyperband.py
autotorch/scheduler/hyperband_promotion.py
autotorch/scheduler/hyperband_stopping.py
autotorch/scheduler/reporter.py
autotorch/scheduler/scheduler.py
autotorch/scheduler/remote/__init__.py
autotorch/scheduler/remote/cli.py
autotorch/scheduler/remote/dask_scheduler.py
autotorch/scheduler/remote/remote.py
autotorch/scheduler/remote/remote_manager.py
autotorch/scheduler/remote/ssh_helper.py
autotorch/scheduler/resource/__init__.py
autotorch/scheduler/resource/dist_manager.py
autotorch/scheduler/resource/manager.py
autotorch/scheduler/resource/nvutil.py
autotorch/scheduler/resource/resource.py
autotorch/searcher/__init__.py
autotorch/searcher/grid_searcher.py
autotorch/searcher/searcher.py
autotorch/searcher/searcher_factory.py
autotorch/utils/__init__.py
autotorch/utils/custom_process.py
autotorch/utils/custom_queue.py
autotorch/utils/defaultdict.py
autotorch/utils/deprecate.py
autotorch/utils/edict.py
autotorch/utils/files.py
autotorch/utils/miscs.py
autotorch/utils/serialization.py
autotorch/utils/sync_remote.py
autotorch/utils/tqdm.py
autotorch/utils/util_decorator.py
AutoTorch-0.0.1.dist-info/LICENSE
AutoTorch-0.0.1.dist-info/METADATA
AutoTorch-0.0.1.dist-info/WHEEL
AutoTorch-0.0.1.dist-info/entry_points.txt
AutoTorch-0.0.1.dist-info/top_level.txt
AutoTorch-0.0.1.dist-info/RECORD
