Metadata-Version: 2.1
Name: AutoTorch
Version: 0.0.1
Summary: AutoTorch Package
Home-page: https://github.com/StacyYang/AutoTorch
Author: AutoTorch Community
License: Apache-2.0
Platform: UNKNOWN
Requires-Dist: numpy
Requires-Dist: cython
Requires-Dist: requests
Requires-Dist: matplotlib
Requires-Dist: dask (>=2.6.0)
Requires-Dist: tqdm (>=4.38.0)
Requires-Dist: paramiko (~=2.4)
Requires-Dist: tornado (>=5.0.1)
Requires-Dist: distributed (>=2.6.0)
Requires-Dist: ConfigSpace (<=0.4.11)
Requires-Dist: nose
